MANIFEST.in
README.rst
requirements.txt
setup.py
test-requirements.txt
lightpack/__init__.py
lightpack/version.py
lightpack.egg-info/PKG-INFO
lightpack.egg-info/SOURCES.txt
lightpack.egg-info/dependency_links.txt
lightpack.egg-info/top_level.txt