Metadata-Version: 1.1
Name: lightpack
Version: 0.0.1
Summary: Controls Lightpack devices through a common Python API
Home-page: https://github.com/briancline/lightpack
Author: Brian Cline
Author-email: brian.cline@gmail.com
License: MIT
Keywords: lightpack api
Platform: UNKNOWN
Classifier: Development Status :: 2 - Pre-Alpha
Classifier: License :: OSI Approved :: MIT License
Classifier: Intended Audience :: Developers
Classifier: Intended Audience :: System Administrators
Classifier: Natural Language :: English
Classifier: Operating System :: POSIX :: Linux
Classifier: Operating System :: Unix
Classifier: Programming Language :: Python
Classifier: Programming Language :: Python :: 2
Classifier: Programming Language :: Python :: 2.7
Classifier: Programming Language :: Python :: 3
Classifier: Programming Language :: Python :: 3.2
Classifier: Programming Language :: Python :: 3.3
Classifier: Topic :: Home Automation
